docker_patch/__init__.py
docker_patch/__main__.py
tests/__init__.py
tests/data.py
tests/test_cli.py
tests/test_package.py
docker_patch-0.1.2.dist-info/METADATA
docker_patch-0.1.2.dist-info/WHEEL
docker_patch-0.1.2.dist-info/entry_points.txt
docker_patch-0.1.2.dist-info/top_level.txt
docker_patch-0.1.2.dist-info/RECORD
