Metadata-Version: 2.1
Name: docker-patch
Version: 0.1.2
Summary: Patch docker images to fit your purposes and organization requirements
Home-page: https://github.com/AvivAbramovich/docker-patch
Author: Aviv Abramovich
Author-email: AvivAbramovich@gmail.com
License: UNKNOWN
Platform: UNKNOWN
Requires-Dist: certifi (==2020.12.5)
Requires-Dist: chardet (==4.0.0)
Requires-Dist: click (==7.1.2)
Requires-Dist: docker (==5.0.0)
Requires-Dist: idna (==2.10)
Requires-Dist: requests (==2.25.1)
Requires-Dist: six (==1.15.0)
Requires-Dist: urllib3 (==1.26.4)
Requires-Dist: websocket-client (==0.58.0)
